CHANGES.txt
CREDITS.txt
MANIFEST.in
README.txt
setup.py
src/hurry/__init__.py
src/hurry.raphael.egg-info/PKG-INFO
src/hurry.raphael.egg-info/SOURCES.txt
src/hurry.raphael.egg-info/dependency_links.txt
src/hurry.raphael.egg-info/entry_points.txt
src/hurry.raphael.egg-info/namespace_packages.txt
src/hurry.raphael.egg-info/not-zip-safe
src/hurry.raphael.egg-info/requires.txt
src/hurry.raphael.egg-info/top_level.txt
src/hurry/raphael/__init__.py
src/hurry/raphael/_lib.py
src/hurry/raphael/configure.zcml
src/hurry/raphael/prepare.py
src/hurry/raphael/raphael.txt
src/hurry/raphael/tests.py
src/hurry/raphael/raphael-build/raphael-min.js
src/hurry/raphael/raphael-build/raphael.js