Metadata-Version: 1.0
Name: hurry.raphael
Version: 1.4.3.1
Summary: hurry.resource style resources for Raphael.
Home-page: http://github.com/jmichiel/hurry.raphael
Author: Jeroen Michiel
Author-email: jmichiel@yahoo.com
License: UNKNOWN
Platform: UNKNOWN
